MANIFEST.in
TODO.txt
setup.py
starscream.py
StarScream.egg-info/PKG-INFO
StarScream.egg-info/SOURCES.txt
StarScream.egg-info/dependency_links.txt
StarScream.egg-info/requires.txt
StarScream.egg-info/top_level.txt
starscreamlib/__init__.py
starscreamlib/common.py
starscreamlib/docutilslib.py
starscreamlib/handout.css
starscreamlib/handout.py
starscreamlib/slide.css
starscreamlib/slides.py
starscreamlib/slides.txt
starscreamlib/syntax.css
starscreamlib/scripts/jquery.dimensions.js
starscreamlib/scripts/jquery.gradient.js
starscreamlib/scripts/jquery.js
starscreamlib/scripts/scripts.js
