Metadata-Version: 1.0
Name: StarScream
Version: 0.1.3
Summary: StarScream is a presentation tool
Home-page: http://starscream-slideshow.googlecode.com/
Author: Feihong Hsu
Author-email: UNKNOWN
License: New BSD
Keywords: presentation slideshow handout reStructuredText
Platform: UNKNOWN
